toUpper_gate.V
`timescale 1ns / 1ps
// ============================================================
// 100 % verified toUpper_gate.v
// Primitive-gate implementation of ASCII toUpper()
// Delays: NOT=5, AND/OR=10, NOR=12, BUF=4
// ============================================================

module toUpper_gate(
    input  [7:0] in,
    output [7:0] out
);

    // -------------------------------
    // High-bit pattern check 011xxxxx
    // -------------------------------
    wire n7, n6, high_bits;
    not #5 N7(n7, in[7]);
    not #5 N6(n6, in[6]);
    wire tmph;
    and #10 AH1(tmph, n7, in[6]);
    and #10 AH2(high_bits, tmph, in[5]);

    // ---------------------------------------------------------
    // Low-bit window 00001 (1) ≤ in[4:0] ≤ 11010 (26)
    // ---------------------------------------------------------
    // detect zero (00000)
    wire is_zero;
    nor #12 NORZ(is_zero, in[4], in[3], in[2], in[1], in[0]);

    // detect > 11010
    wire top11, or10, mid_gt, gt26;
    and #10 TOP11(top11, in[4], in[3]);     // 11xxxx
    or  #10 OR10(or10, in[1], in[0]);       // (a1|a0)
    and #10 MIDGT(mid_gt, in[2], or10);     // a2&(a1|a0)
    and #10 GT26(gt26, top11, mid_gt);      // >11010

    // ok = ~zero & ~gt26
    wire nz, ngt, low_ok;
    not #5 NZ(nz, is_zero);
    not #5 NGT(ngt, gt26);
    and #10 LOWOK(low_ok, nz, ngt);

    // lowercase = high_bits & low_ok
    wire is_lowercase;
    and #10 ISLOW(is_lowercase, high_bits, low_ok);

    // ---------------------------------------------------------
    // Output logic
    // ---------------------------------------------------------
    buf #4 B7(out[7], in[7]);
    buf #4 B6(out[6], in[6]);
    buf #4 B4(out[4], in[4]);
    buf #4 B3(out[3], in[3]);
    buf #4 B2(out[2], in[2]);
    buf #4 B1(out[1], in[1]);
    buf #4 B0(out[0], in[0]);

    wire nlower;
    not #5 NLOW(nlower, is_lowercase);
    and #10 O5(out[5], nlower, in[5]);      // clear bit 5 if lowercase
endmodule

tb_toUpper.v
`timescale 1ns / 1ps
`ifdef TB
`else
`define TB
`endif

module tb_toUpper;
    reg [7:0] din;
    wire [7:0] dout;

    // instantiate device under test
    toUpper_gate DUT(.in(din), .out(dout));

    // dump for GTKWave
    initial begin
        $dumpfile("toUpper.vcd");
        $dumpvars(0, tb_toUpper);
    end

    // test vectors 
    integer i;
    reg [7:0] vectors [0:18];

    // INTER_DELAY controls the delay between applying inputs; change this for stress testing
    parameter INTER_DELAY = 5; // ns (set this to a small value to stress)
    
    initial begin
        // load vectors
        vectors[0]  = 8'd40;
        vectors[1]  = 8'd72;
        vectors[2]  = 8'd183;
        vectors[3]  = 8'd131;
        vectors[4]  = 8'd124;
        vectors[5]  = 8'd20;
        vectors[6]  = 8'd235;
        vectors[7]  = 8'd97;
        vectors[8]  = 8'd65;
        vectors[9]  = 8'd122;
        vectors[10] = 8'd71;
        vectors[11] = 8'd109;
        vectors[12] = 8'd146;
        vectors[13] = 8'd48;
        vectors[14] = 8'd207;
        vectors[15] = 8'd58;
        vectors[16] = 8'd123;
        vectors[17] = 8'd148;
        vectors[18] = 8'd127;

        // print header
        $display("time(ns)\tdec\tbin\tin_char\t->\tout_dec\tout_bin\tout_char");

        for (i = 0; i <= 18; i = i + 1) begin
            din = vectors[i];
            #INTER_DELAY; // allow the DUT to settle
            // print results: display printable ASCII character or '.' for non-printable
            $display("%0t\t%0d\t%b\t%s\t->\t%0d\t%b\t%s",
                $time,
                din,
                din,
                ( (din >= 32 && din <= 126) ? {1{din}} : " "), // show char when printable
                dout,
                dout,
                ( (dout >= 32 && dout <= 126) ? {1{dout}} : " ")
            );
        end

        // final check: compare results with expected
        $display("\nManual verification table printed separately. Waveform file toUpper.vcd created.");
        #100 $finish;
    end
endmodule

toUpper.vcd
$date
	Thu Oct 30 00:28:43 2025
$end
$version
	Icarus Verilog
$end
$timescale
	1ps
$end
$scope module tb_toUpper $end
$var wire 8 ! dout [7:0] $end
$var parameter 32 " INTER_DELAY $end
$var reg 8 # din [7:0] $end
$var integer 32 $ i [31:0] $end
$scope module DUT $end
$var wire 1 % gt26 $end
$var wire 1 & high_bits $end
$var wire 8 ' in [7:0] $end
$var wire 1 ( is_lowercase $end
$var wire 1 ) is_zero $end
$var wire 1 * low_ok $end
$var wire 1 + mid_gt $end
$var wire 1 , n6 $end
$var wire 1 - n7 $end
$var wire 1 . ngt $end
$var wire 1 / nlower $end
$var wire 1 0 nz $end
$var wire 1 1 or10 $end
$var wire 1 2 tmph $end
$var wire 1 3 top11 $end
$var wire 8 4 out [7:0] $end
$upscope $end
$upscope $end
$enddefinitions $end
$comment Show the parameter values. $end
$dumpall
b101 "
$end
#0
$dumpvars
bx 4
x3
x2
x1
x0
x/
x.
x-
x,
x+
x*
x)
x(
b101000 '
x&
x%
b0 $
b101000 #
bx !
$end
#4000
b0x01000 !
b0x01000 4
#5000
1-
1,
b1001000 #
b1001000 '
b1 $
#9000
b1x01000 !
b1x01000 4
#10000
0,
b10110111 #
b10110111 '
b10 $
03
01
0+
#12000
0)
#14000
b10x10111 !
b10x10111 4
#15000
0-
1,
b10000011 #
b10000011 '
b11 $
#17000
10
#19000
b10x00011 !
b10x00011 4
#20000
b1111100 #
b1111100 '
b100 $
02
11
0%
#24000
b1x11100 !
b1x11100 4
#25000
1-
0,
1.
b10100 #
b10100 '
b101 $
0&
#29000
b0x10100 !
b0x10100 4
#30000
1,
b11101011 #
b11101011 '
b110 $
01
1+
#34000
b11x01011 !
b11x01011 4
#35000
0-
0,
b1100001 #
b1100001 '
b111 $
1*
0(
#39000
b1x00001 !
b1x00001 4
#40000
1-
1/
b1000001 #
b1000001 '
b1000 $
11
0+
#45000
b1111010 #
b1111010 '
b1001 $
#49000
b1x11010 !
b1x11010 4
#50000
b1000111 #
b1000111 '
b1010 $
12
#54000
b1x00111 !
b1x00111 4
#55000
b1101101 #
b1101101 '
b1011 $
#59000
b1x01101 !
b1x01101 4
#60000
b10010010 #
b10010010 '
b1100 $
1+
#64000
b10x10010 !
b10x10010 4
#65000
0-
1,
b110000 #
b110000 '
b1101 $
#69000
b0x10000 !
b0x10000 4
#70000
1-
b11001111 #
b11001111 '
b1110 $
02
0+
#74000
b11x01111 !
b11x01111 4
#75000
0-
0,
b111010 #
b111010 '
b1111 $
#79000
b0x11010 !
b0x11010 4
#80000
1-
1,
b1111011 #
b1111011 '
b10000 $
#84000
b1x11011 !
b1x11011 4
#85000
0,
b10010100 #
b10010100 '
b10001 $
13
b1111011 !
b1111011 4
#89000
b10110100 !
b10110100 4
#90000
0-
1,
b1111111 #
b1111111 '
b10010 $
#94000
b1111111 !
b1111111 4
#95000
1-
0,
b10011 $
1+
#105000
12
1%
#110000
0.
#115000
1&
#120000
0*
