toUpper.v
/*
 * `toUpper.v`
 * Implements an 8-bit toUpper() function using only primitive
 * gate instantiations with specified propagation delays.
 *

 */
`timescale 1ns / 1ps

module toUpper (
    output [7:0] O,
    input [7:0] I
);

    // Delays
    localparam DELAY_NOT = 5;
    localparam DELAY_AND = 10;
    localparam DELAY_OR  = 10;
    localparam DELAY_XOR = 15;
    localparam DELAY_BUF = 4;

    // --- Final Output Logic ---
    wire is_lowercase, not_is_lowercase;
    
    // Pass-through for bits 0, 1, 2, 3, 4, 6, 7
    buf #(DELAY_BUF) B0 (O[0], I[0]);
    buf #(DELAY_BUF) B1 (O[1], I[1]);
    buf #(DELAY_BUF) B2 (O[2], I[2]);
    buf #(DELAY_BUF) B3 (O[3], I[3]);
    buf #(DELAY_BUF) B4 (O[4], I[4]);
    buf #(DELAY_BUF) B6 (O[6], I[6]);
    buf #(DELAY_BUF) B7 (O[7], I[7]);

    // Gating logic for bit 5
    // O[5] = I[5] AND (NOT is_lowercase)
    not #(DELAY_NOT) NOT_IS_LC (not_is_lowercase, is_lowercase);
    and #(DELAY_AND) GATED_BIT5 (O[5], I[5], not_is_lowercase);


    // --- `is_lowercase` Logic ---
    // is_lowercase = (I >= 97) AND (I <= 122)
    wire gte_97, lte_122;
    and #(DELAY_AND) IS_LC (is_lowercase, gte_97, lte_122);

    // --- Comparator 1: I >= 97 (01100001) ---
    wire gt_97, eq_97;
    wire [7:0] x; // x[i] = I[i] XNOR B[i]
    
    // B[7:0] = 01100001
    not #(DELAY_NOT) X7 (x[7], I[7]); // I[7] XNOR 0
    buf #(DELAY_BUF) X6 (x[6], I[6]); // I[6] XNOR 1
    buf #(DELAY_BUF) X5 (x[5], I[5]); // I[5] XNOR 1
    not #(DELAY_NOT) X4 (x[4], I[4]); // I[4] XNOR 0
    not #(DELAY_NOT) X3 (x[3], I[3]); // I[3] XNOR 0
    not #(DELAY_NOT) X2 (x[2], I[2]); // I[2] XNOR 0
    not #(DELAY_NOT) X1 (x[1], I[1]); // I[1] XNOR 0
    buf #(DELAY_BUF) X0 (x[0], I[0]); // I[0] XNOR 1

    // eq_97 = (I == 97) = x[7] & x[6] & ... & x[0] (AND tree)
    wire x7_6, x5_4, x3_2, x1_0, x7_4, x3_0;
    and #(DELAY_AND) EQ1 (x7_6, x[7], x[6]);
    and #(DELAY_AND) EQ2 (x5_4, x[5], x[4]);
    and #(DELAY_AND) EQ3 (x3_2, x[3], x[2]);
    and #(DELAY_AND) EQ4 (x1_0, x[1], x[0]);
    and #(DELAY_AND) EQ5 (x7_4, x7_6, x5_4);
    and #(DELAY_AND) EQ6 (x3_0, x3_2, x1_0);
    and #(DELAY_AND) EQ_97 (eq_97, x7_4, x3_0);

    // gt_97 = (I > 97) = I[7]B'[7] + x[7]I[6]B'[6] + x[7]x[6]I[5]B'[5] + ...
    // B_97 = 01100001. B'[7]=1, B'[6]=0, B'[5]=0, B'[4]=1, B'[3]=1, B'[2]=1, B'[1]=1, B'[0]=0
    wire t1, t4, t5, t6, t7;
    wire t4_a, t4_b, t5_a, t5_b, t6_a, t6_b, t7_a, t7_b; // intermediate ANDs
    
    buf #(DELAY_BUF) GT_T1 (t1, I[7]);  // t1 = I[7] & 1
    
    and #(DELAY_AND) T4A (t4_a, x[7], x[6]);
    and #(DELAY_AND) T4B (t4_b, t4_a, x[5]);
    and #(DELAY_AND) GT_T4 (t4, t4_b, I[4]); // t4 = x[7..5] & I[4] & 1
    
    and #(DELAY_AND) T5A (t5_a, t4_b, x[4]);
    and #(DELAY_AND) GT_T5 (t5, t5_a, I[3]); // t5 = x[7..4] & I[3] & 1

    and #(DELAY_AND) T6A (t6_a, t5_a, x[3]);
    and #(DELAY_AND) GT_T6 (t6, t6_a, I[2]); // t6 = x[7..3] & I[2] & 1
    
    and #(DELAY_AND) T7A (t7_a, t6_a, x[2]);
    and #(DELAY_AND) GT_T7 (t7, t7_a, I[1]); // t7 = x[7..2] & I[1] & 1
    
    // OR tree for gt_97 = t1 | t4 | t5 | t6 | t7
    wire or1, or2, or3;
    or #(DELAY_OR) GT_OR1 (or1, t1, t4);
    or #(DELAY_OR) GT_OR2 (or2, t5, t6);
    or #(DELAY_OR) GT_OR3 (or3, or2, t7);
    or #(DELAY_OR) GT_97 (gt_97, or1, or3);
    
    // gte_97 = (I > 97) OR (I == 97)
    or #(DELAY_OR) GTE_97 (gte_97, gt_97, eq_97);


    // --- Comparator 2: I <= 122 (01111010) ---
    wire lt_122, eq_122;
    wire [7:0] y; // y[i] = I[i] XNOR B[i]
    
    // B[7:0] = 01111010
    not #(DELAY_NOT) Y7 (y[7], I[7]); // I[7] XNOR 0
    buf #(DELAY_BUF) Y6 (y[6], I[6]); // I[6] XNOR 1
    buf #(DELAY_BUF) Y5 (y[5], I[5]); // I[5] XNOR 1
    buf #(DELAY_BUF) Y4 (y[4], I[4]); // I[4] XNOR 1
    buf #(DELAY_BUF) Y3 (y[3], I[3]); // I[3] XNOR 1
    not #(DELAY_NOT) Y2 (y[2], I[2]); // I[2] XNOR 0
    buf #(DELAY_BUF) Y1 (y[1], I[1]); // I[1] XNOR 1
    not #(DELAY_NOT) Y0 (y[0], I[0]); // I[0] XNOR 0

    // eq_122 = (I == 122) = y[7] & y[6] & ... & y[0] (AND tree)
    wire y7_6, y5_4, y3_2, y1_0, y7_4, y3_0;
    and #(DELAY_AND) EQ1_122 (y7_6, y[7], y[6]);
    and #(DELAY_AND) EQ2_122 (y5_4, y[5], y[4]);
    and #(DELAY_AND) EQ3_122 (y3_2, y[3], y[2]);
    and #(DELAY_AND) EQ4_122 (y1_0, y[1], y[0]);
    and #(DELAY_AND) EQ5_122 (y7_4, y7_6, y5_4);
    and #(DELAY_AND) EQ6_122 (y3_0, y3_2, y1_0);
    and #(DELAY_AND) EQ_122 (eq_122, y7_4, y3_0);

    // lt_122 = (I < 122) = I'[7]B[7] + y[7]I'[6]B[6] + y[7]y[6]I'[5]B'[5] + ...
    // B_122 = 01111010.
    wire lt_t2, lt_t3, lt_t4, lt_t5, lt_t7;
    wire not_I6, not_I5, not_I4, not_I3, not_I1;
    wire lt_a2, lt_a3, lt_a4, lt_a5, lt_a7_int, lt_a7;
    
    // t1 = I'[7] & B[7] = I'[7] & 0 = 0
    not #(DELAY_NOT) NI6 (not_I6, I[6]);
    and #(DELAY_AND) LT_T2 (lt_t2, y[7], not_I6); // t2 = y[7] & I'[6] & 1
    
    not #(DELAY_NOT) NI5 (not_I5, I[5]);
    and #(DELAY_AND) LT_A3 (lt_a3, y[7], y[6]);
    and #(DELAY_AND) LT_T3 (lt_t3, lt_a3, not_I5); // t3 = y[7..6] & I'[5] & 1
    
    not #(DELAY_NOT) NI4 (not_I4, I[4]);
    and #(DELAY_AND) LT_A4 (lt_a4, lt_a3, y[5]);
    and #(DELAY_AND) LT_T4 (lt_t4, lt_a4, not_I4); // t4 = y[7..5] & I'[4] & 1
    
    not #(DELAY_NOT) NI3 (not_I3, I[3]);
    and #(DELAY_AND) LT_A5 (lt_a5, lt_a4, y[4]);
    and #(DELAY_AND) LT_T5 (lt_t5, lt_a5, not_I3); // t5 = y[7..4] & I'[3] & 1

    // t6 = y[7..3] & I'[2] & B[2] = ... & 0 = 0
    
    not #(DELAY_NOT) NI1 (not_I1, I[1]);
    and #(DELAY_AND) LT_A7_int (lt_a7_int, lt_a5, y[3]);
    and #(DELAY_AND) LT_A7 (lt_a7, lt_a7_int, y[2]); // This was the missing term
    and #(DELAY_AND) LT_T7 (lt_t7, lt_a7, not_I1); // t7 = y[7..3] & y[2] & I'[1] & 1
  
    
    // t8 = ... & B[0] = ... & 0 = 0
    
    // OR tree for lt_122 = t2 | t3 | t4 | t5 | t7
    wire lt_or1, lt_or2, lt_or3;
    or #(DELAY_OR) LT_OR1 (lt_or1, lt_t2, lt_t3);
    or #(DELAY_OR) LT_OR2 (lt_or2, lt_t4, lt_t5);
    or #(DELAY_OR) LT_OR3 (lt_or3, lt_or2, lt_t7);
    or #(DELAY_OR) LT_122 (lt_122, lt_or1, lt_or3);
    
    // lte_122 = (I < 122) OR (I == 122)
    or #(DELAY_OR) LTE_122 (lte_122, lt_122, eq_122);
    
endmodule

tb_toUpper.v
/*
 * `tb_toUpper.v`
 * Test bench for the toUpper module.
 * This test bench will:
 * 1. Instantiate the `toUpper` module.
 * 2. Provide all 20 test case inputs from the project description.
 * 3. Monitor and print the inputs and outputs to the console.
 * 4. Generate a waveform file `waveform.vcd` for analysis.
 * 5. Use a parameter `INTER_INPUT_DELAY` for stress testing.
 */
`timescale 1ns / 1ps

module tb_toUpper;

  // This parameter controls the time between test inputs.iverilog -o toUpper_tb.vvp toUpper.v tb_toUpper.v
  parameter INTER_INPUT_DELAY = 120; // Was 99

  // Inputs to the UUT (Unit Under Test)
  reg [7:0] input_char;

  // Outputs from the UUT
  wire [7:0] output_char;

  // Instantiate the Unit Under Test
  toUpper UUT (
            .O(output_char),
            .I(input_char)
          );

  // Initial block to provide stimulus
  initial
  begin
    // Setup waveform dumping
    $dumpfile("waveform.vcd");
    $dumpvars(0, tb_toUpper);

    // Monitor to print changes to the console
    $monitor("Time = %0t ns | Input: %d (%b) | Output: %d (%b)",
             $time, input_char, input_char, output_char, output_char);

    // --- Start Test Cases ---
    // ( 40
    #INTER_INPUT_DELAY input_char = 40;
    // H 72
    #INTER_INPUT_DELAY input_char = 72;
    // · 183
    #INTER_INPUT_DELAY input_char = 183;
    // ƒ 131
    #INTER_INPUT_DELAY input_char = 131;
    // | 124
    #INTER_INPUT_DELAY input_char = 124;
    // DC4 20
    #INTER_INPUT_DELAY input_char = 20;
    // ë 235
    #INTER_INPUT_DELAY input_char = 235;
    // a 97  -> should convert to 65
    #INTER_INPUT_DELAY input_char = 97;
    // A 65
    #INTER_INPUT_DELAY input_char = 65;
    // z 122 -> should convert to 90
    #INTER_INPUT_DELAY input_char = 122;
    // G 71
    #INTER_INPUT_DELAY input_char = 71;
    // m 109 -> should convert to 77
    #INTER_INPUT_DELAY input_char = 109;
    // ' 146
    #INTER_INPUT_DELAY input_char = 146;
    // 0 48
    #INTER_INPUT_DELAY input_char = 48;
    // Ï 207
    #INTER_INPUT_DELAY input_char = 207;
    // : 58
    #INTER_INPUT_DELAY input_char = 58;
    // { 123
    #INTER_INPUT_DELAY input_char = 123;
    // ” 148
    #INTER_INPUT_DELAY input_char = 148;
    // DEL 127
    #INTER_INPUT_DELAY input_char = 127;

    // Add one last delay to see the final output clearly
    #INTER_INPUT_DELAY;

    // Finish the simulation
    $finish;
  end

endmodule

waveform.vcd
$date
	Thu Oct 30 12:47:46 2025
$end
$version
	Icarus Verilog
$end
$timescale
	1ps
$end
$scope module tb_toUpper $end
$var wire 8 ! output_char [7:0] $end
$var parameter 32 " INTER_INPUT_DELAY $end
$var reg 8 # input_char [7:0] $end
$scope module UUT $end
$var wire 8 $ I [7:0] $end
$var wire 1 % eq_122 $end
$var wire 1 & eq_97 $end
$var wire 1 ' gt_97 $end
$var wire 1 ( gte_97 $end
$var wire 1 ) is_lowercase $end
$var wire 1 * lt_122 $end
$var wire 1 + lt_a3 $end
$var wire 1 , lt_a4 $end
$var wire 1 - lt_a5 $end
$var wire 1 . lt_a7 $end
$var wire 1 / lt_a7_int $end
$var wire 1 0 lt_or1 $end
$var wire 1 1 lt_or2 $end
$var wire 1 2 lt_or3 $end
$var wire 1 3 lt_t2 $end
$var wire 1 4 lt_t3 $end
$var wire 1 5 lt_t4 $end
$var wire 1 6 lt_t5 $end
$var wire 1 7 lt_t7 $end
$var wire 1 8 lte_122 $end
$var wire 1 9 not_I1 $end
$var wire 1 : not_I3 $end
$var wire 1 ; not_I4 $end
$var wire 1 < not_I5 $end
$var wire 1 = not_I6 $end
$var wire 1 > not_is_lowercase $end
$var wire 1 ? or1 $end
$var wire 1 @ or2 $end
$var wire 1 A or3 $end
$var wire 1 B t1 $end
$var wire 1 C t4 $end
$var wire 1 D t4_a $end
$var wire 1 E t4_b $end
$var wire 1 F t5 $end
$var wire 1 G t5_a $end
$var wire 1 H t6 $end
$var wire 1 I t6_a $end
$var wire 1 J t7 $end
$var wire 1 K t7_a $end
$var wire 1 L x1_0 $end
$var wire 1 M x3_0 $end
$var wire 1 N x3_2 $end
$var wire 1 O x5_4 $end
$var wire 1 P x7_4 $end
$var wire 1 Q x7_6 $end
$var wire 1 R y1_0 $end
$var wire 1 S y3_0 $end
$var wire 1 T y3_2 $end
$var wire 1 U y5_4 $end
$var wire 1 V y7_4 $end
$var wire 1 W y7_6 $end
$var wire 8 X y [7:0] $end
$var wire 8 Y x [7:0] $end
$var wire 8 Z O [7:0] $end
$var parameter 32 [ DELAY_AND $end
$var parameter 32 \ DELAY_BUF $end
$var parameter 32 ] DELAY_NOT $end
$var parameter 32 ^ DELAY_OR $end
$var parameter 32 _ DELAY_XOR $end
$upscope $end
$upscope $end
$enddefinitions $end
$comment Show the parameter values. $end
$dumpall
b1111 _
b1010 ^
b101 ]
b100 \
b1010 [
b1111000 "
$end
#0
$dumpvars
bx Z
bx Y
bx X
xW
xV
xU
xT
xS
xR
xQ
xP
xO
xN
xM
xL
xK
xJ
xI
xH
xG
xF
xE
xD
xC
xB
xA
x@
x?
x>
x=
x<
x;
x:
x9
x8
x7
x6
x5
x4
x3
x2
x1
x0
x/
x.
x-
x,
x+
x*
x)
x(
x'
x&
x%
bx $
bx #
bx !
$end
#120000
b101000 #
b101000 $
#124000
b0x01000 !
b0x01000 Z
bx01xxxx0 Y
bx0101x0x X
0B
#125000
b10110110 Y
b10101101 X
1=
0<
1;
0:
19
#130000
0C
0H
0J
#134000
0Q
0L
0D
0W
0U
0R
0+
0-
#135000
1O
0N
0I
1T
13
04
06
#140000
0?
#144000
0P
0M
0E
0V
0S
0,
0/
#145000
0K
10
#154000
0&
0G
0%
05
0.
#155000
1*
#164000
0F
01
07
#165000
18
#174000
0@
02
#184000
0A
#194000
0'
#204000
0(
#214000
0)
#219000
1>
#229000
b101000 !
b101000 Z
#240000
b1001000 #
b1001000 $
#244000
b1101000 !
b1101000 Z
b11010110 Y
b11001101 X
#245000
0=
1<
#250000
b1001000 !
b1001000 Z
#254000
1Q
0O
1D
1W
1+
#255000
03
#264000
14
#360000
b10110111 #
b10110111 $
#364000
b10010111 !
b10010111 Z
b10110111 Y
b10110111 X
1B
#365000
b101001 Y
b110010 X
1=
0<
0;
1:
09
#370000
b10110111 !
b10110111 Z
#374000
0Q
0D
1E
0W
1U
0T
0+
1,
1?
#375000
04
#384000
0E
1C
0,
1-
1'
#385000
00
#394000
0C
0-
16
1(
#395000
0*
#404000
06
11
1)
#405000
08
#409000
0>
#414000
01
12
#415000
0)
#419000
b10010111 !
b10010111 Z
#420000
1>
#424000
02
1*
#430000
b10110111 !
b10110111 Z
#434000
0*
18
#444000
08
1)
#449000
0>
#454000
0)
#459000
b10010111 !
b10010111 Z
1>
#469000
b10110111 !
b10110111 Z
#480000
b10000011 #
b10000011 $
#484000
b10100011 !
b10100011 Z
b1001 Y
b10 X
#485000
b11101 Y
b110 X
1<
1;
#490000
b10000011 !
b10000011 Z
#494000
0U
#495000
1N
#600000
b1111100 #
b1111100 $
#604000
b1011100 !
b1011100 Z
b1111100 Y
b1111100 X
0B
#605000
b11100010 Y
b11111001 X
0=
0<
0;
0:
19
#610000
b1111100 !
b1111100 Z
#614000
1U
0?
#615000
1Q
0N
1D
1W
1+
#624000
0'
#625000
1E
1V
1,
#634000
0(
#635000
1C
1-
#645000
1?
1/
#655000
1'
#665000
1(
#720000
b10100 #
b10100 $
#724000
b110100 !
b110100 Z
b10000010 Y
b10010001 X
#725000
b10001010 Y
1=
1<
1:
#730000
b10100 !
b10100 Z
#734000
0Q
0D
0E
0W
0U
0+
0,
0/
#735000
13
16
#744000
0C
0V
0-
#745000
10
11
#754000
0?
06
#755000
1*
12
#764000
0'
01
#765000
18
#774000
0(
02
#840000
b11101011 #
b11101011 $
#844000
b11001011 !
b11001011 Z
b11101011 Y
b11101011 X
1B
#845000
b1110101 Y
b1101110 X
0=
0<
1;
0:
09
#850000
b11101011 !
b11101011 Z
#854000
1?
#855000
1O
1T
03
#864000
1'
#865000
00
#874000
1(
#875000
0*
#884000
1)
#885000
08
#889000
0>
#895000
0)
#899000
b11001011 !
b11001011 Z
#900000
1>
#910000
b11101011 !
b11101011 Z
#960000
b1100001 #
b1100001 $
#964000
b1100001 !
b1100001 Z
b1100100 X
0B
#965000
b11111111 Y
b11100100 X
1:
19
#974000
0T
0?
#975000
1Q
1N
1L
1D
1W
1+
#984000
0'
#985000
1P
1M
1E
1,
#994000
0(
#995000
1&
1G
15
#1005000
1(
1I
11
#1015000
1K
12
#1025000
1*
#1035000
18
#1045000
1)
#1050000
0>
#1060000
b1000001 !
b1000001 Z
#1080000
b1000001 #
b1000001 $
#1084000
b11011111 Y
b11000100 X
#1085000
1<
#1094000
0O
0E
0,
#1095000
14
#1104000
0P
0G
05
#1105000
10
#1114000
0&
0I
01
#1124000
0(
0K
02
#1134000
0)
#1139000
1>
#1200000
b1111010 #
b1111010 $
#1204000
b1011010 !
b1011010 Z
b11111110 Y
b11111110 X
#1205000
b11100100 Y
b11111111 X
0<
0;
0:
09
#1210000
b1111010 !
b1111010 Z
#1214000
0L
1E
1U
1T
1,
#1215000
0N
1R
04
#1224000
0M
1C
1V
1-
#1225000
1S
00
#1234000
1?
1/
#1235000
1%
0*
#1244000
1'
1.
#1254000
1(
#1264000
1)
#1269000
0>
#1279000
b1011010 !
b1011010 Z
#1320000
b1000111 #
b1000111 $
#1324000
b1000111 !
b1000111 Z
b11000101 Y
b11000111 X
#1325000
b11011001 Y
b11000010 X
1<
1;
1:
#1330000
0C
#1334000
0E
0U
0T
0,
0-
0/
#1335000
0R
0.
14
#1340000
0?
#1344000
0V
0S
#1345000
10
#1350000
0'
#1354000
0%
#1355000
1*
#1360000
0(
#1370000
0)
#1375000
1>
#1440000
b1101101 #
b1101101 $
#1444000
b1001101 !
b1001101 Z
b11111001 Y
b11101000 X
#1445000
b11110011 Y
0<
0:
19
#1450000
b1101101 !
b1101101 Z
#1454000
1O
1E
1,
#1455000
1L
04
#1464000
1P
1G
15
#1465000
00
#1474000
1F
11
#1475000
0*
#1484000
1@
12
#1485000
08
#1494000
1A
1*
#1504000
1'
18
#1514000
1(
#1524000
1)
#1529000
0>
#1539000
b1001101 !
b1001101 Z
#1560000
b10010010 #
b10010010 $
#1564000
b10010010 !
b10010010 Z
b10010010 Y
b10010010 X
1B
#1565000
b1100 Y
b10111 X
1=
1<
0;
1:
09
#1570000
1C
0F
#1574000
0Q
0O
0L
0D
0E
0W
0+
0,
1-
1?
#1575000
1N
0G
1I
1R
05
#1580000
0@
#1584000
0P
0C
0-
16
#1585000
0I
1K
#1590000
0A
#1594000
06
#1595000
0K
1J
#1604000
01
#1605000
0J
1A
#1614000
02
#1615000
0A
#1624000
0*
#1634000
08
#1644000
0)
#1649000
1>
#1680000
b110000 #
b110000 $
#1684000
b10000 !
b10000 Z
b101100 Y
b110101 X
0B
#1685000
b10101110 Y
b10110101 X
0<
19
#1690000
b110000 !
b110000 Z
#1694000
1U
0R
0?
#1695000
13
#1704000
0'
#1705000
10
#1714000
0(
#1715000
1*
#1725000
18
#1800000
b11001111 #
b11001111 $
#1804000
b11101111 !
b11101111 Z
b11001111 Y
b11001111 X
1B
#1805000
b1010001 Y
b1001010 X
0=
1<
1;
0:
09
#1810000
b11001111 !
b11001111 Z
#1814000
0U
1?
#1815000
0N
03
#1824000
1'
#1825000
00
#1834000
1(
#1835000
0*
#1844000
1)
#1845000
08
#1849000
0>
#1855000
0)
#1860000
1>
#1920000
b111010 #
b111010 $
#1924000
b11010 !
b11010 Z
b110000 Y
b111010 X
0B
#1925000
b10100100 Y
b10111111 X
1=
0<
0;
#1930000
b111010 !
b111010 Z
#1934000
1U
0?
#1935000
1T
1R
13
#1944000
0'
#1945000
1S
10
#1954000
0(
#1955000
1*
#1965000
18
#2040000
b1111011 #
b1111011 $
#2044000
b1111011 !
b1111011 Z
b11100101 Y
b11111111 X
#2045000
b11111110 X
0=
#2054000
1Q
1D
1W
1+
#2055000
0R
03
#2064000
1E
1V
1,
#2065000
0S
00
#2074000
1C
1-
#2075000
0*
#2084000
1?
1/
#2085000
08
#2094000
1'
1.
#2104000
1(
#2160000
b10010100 #
b10010100 $
#2164000
b10110100 !
b10110100 Z
b10000100 Y
b10010100 X
1B
#2165000
b1010 Y
b10001 X
1=
1<
1:
19
#2170000
b10010100 !
b10010100 Z
#2174000
0Q
0D
0E
0W
0U
0T
0+
0,
0/
#2175000
0.
16
17
#2184000
0C
0V
0-
#2185000
07
11
12
#2194000
06
#2195000
1*
#2204000
01
#2205000
18
#2214000
02
#2215000
1)
#2220000
0>
#2224000
0*
#2234000
08
#2244000
0)
#2249000
1>
#2280000
b1111111 #
b1111111 $
#2284000
b1011111 !
b1011111 Z
b1101011 Y
b1111011 X
0B
#2285000
b11100001 Y
b11111010 X
0=
0<
0:
09
#2290000
b1111111 !
b1111111 Z
#2294000
1U
0?
#2295000
1Q
1D
1W
1+
#2304000
0'
#2305000
1E
1V
1,
#2314000
0(
#2315000
1C
1-
#2325000
1?
1/
#2335000
1'
#2345000
1(
